README.rst
carphunter.yml
setup.cfg
setup.py
carphunter/__init__.py
carphunter/cache.py
carphunter/carpconf.py
carphunter/itemsearch.py
carphunter/main.py
carphunter/poller.py
carphunter.egg-info/PKG-INFO
carphunter.egg-info/SOURCES.txt
carphunter.egg-info/dependency_links.txt
carphunter.egg-info/entry_points.txt
carphunter.egg-info/requires.txt
carphunter.egg-info/top_level.txt